{
    "Fighter": {
        "FighterID": "545", 
        "Name": "Jeremy Stephens"
    }, 
    "Fighter_stats": {
        "Round1": {
            "Grappling": {
                "Reversals": {
                    "Landed": "0"
                }, 
                "Standups": {
                    "Landed": "1"
                }, 
                "Submissions": {
                    "Attempts": "0"
                }, 
                "Takedowns": {
                    "Attempts": "0", 
                    "Landed": "0"
                }
            }, 
            "Strikes": {
                "Body Significant Strikes": {
                    "Attempts": "6", 
                    "Landed": "4"
                }, 
                "Body Total Strikes": {
                    "Attempts": "10", 
                    "Landed": "8"
                }, 
                "Clinch Body Strikes": {
                    "Attempts": "2", 
                    "Landed": "1"
                }, 
                "Clinch Head Strikes": {
                    "Attempts": "2", 
                    "Landed": "2"
                }, 
                "Clinch Leg Strikes": {
                    "Attempts": "0", 
                    "Landed": "0"
                }, 
                "Clinch Significant Kicks": {
                    "Attempts": "0", 
                    "Landed": "0"
                }, 
                "Clinch Significant Punches": {
                    "Attempts": "2", 
                    "Landed": "2"
                }, 
                "Clinch Significant Strikes": {
                    "Attempts": "4", 
                    "Landed": "3"
                }, 
                "Clinch Total Strikes": {
                    "Attempts": "4", 
                    "Landed": "3"
                }, 
                "Distance Body Kicks": {
                    "Attempts": "2", 
                    "Landed": "2"
                }, 
                "Distance Body Punches": {
                    "Attempts": "1", 
                    "Landed": "0"
                }, 
                "Distance Body Strikes": {
                    "Attempts": "4", 
                    "Landed": "3"
                }, 
                "Distance Head Kicks": {
                    "Attempts": "2", 
                    "Landed": "0"
                }, 
                "Distance Head Punches": {
                    "Attempts": "49", 
                    "Landed": "15"
                }, 
                "Distance Head Strikes": {
                    "Attempts": "60", 
                    "Landed": "10"
                }, 
                "Distance Leg Kicks": {
                    "Attempts": "13", 
                    "Landed": "11"
                }, 
                "Distance Leg Strikes": {
                    "Attempts": "18", 
                    "Landed": "9"
                }, 
                "Distance Strikes": {
                    "Attempts": "82", 
                    "Landed": "22"
                }, 
                "Ground Body Strikes": {
                    "Attempts": "3", 
                    "Landed": "3"
                }, 
                "Ground Head Strikes": {
                    "Attempts": "4", 
                    "Landed": "3"
                }, 
                "Ground Leg Strikes": {
                    "Attempts": "0", 
                    "Landed": "0"
                }, 
                "Ground Significant Kicks": {
                    "Attempts": "0", 
                    "Landed": "0"
                }, 
                "Ground Significant Punches": {
                    "Attempts": "5", 
                    "Landed": "4"
                }, 
                "Ground Significant Strikes": {
                    "Attempts": "4", 
                    "Landed": "3"
                }, 
                "Ground Total Strikes": {
                    "Attempts": "8", 
                    "Landed": "7"
                }, 
                "Head Significant Strikes": {
                    "Attempts": "66", 
                    "Landed": "15"
                }, 
                "Head Total Strikes": {
                    "Attempts": "66", 
                    "Landed": "15"
                }, 
                "Kicks": {
                    "Attempts": "17", 
                    "Landed": "13"
                }, 
                "Knock Down": {
                    "Landed": "0"
                }, 
                "Leg Total Strikes": {
                    "Attempts": "8", 
                    "Landed": "4"
                }, 
                "Legs Significant Strikes": {
                    "Attempts": "18", 
                    "Landed": "9"
                }, 
                "Legs Total Strikes": {
                    "Attempts": "10", 
                    "Landed": "5"
                }, 
                "Punches": {
                    "Attempts": "62", 
                    "Landed": "24"
                }, 
                "Significant Strikes": {
                    "Attempts": "90", 
                    "Landed": "28"
                }, 
                "Total Strikes": {
                    "Attempts": "94", 
                    "Landed": "32"
                }
            }, 
            "TIP": {
                "Back Control Time": "0.0", 
                "Clinch Time": "168.0", 
                "Control Time": "75.0", 
                "Distance Time": "574.0", 
                "Ground Control Time": "67.0", 
                "Ground Time": "157.0", 
                "Guard Control Time": "45.0", 
                "Half Guard Control Time": "7.0", 
                "Misc. Ground Control Time": "3.0", 
                "Mount Control Time": "12.0", 
                "Neutral Time": "582.0", 
                "Side Control Time": "0.0", 
                "Standing Time": "742.0"
            }
        }, 
        "Round2": {
            "Grappling": {
                "Reversals": {
                    "Landed": "0"
                }, 
                "Standups": {
                    "Landed": "0"
                }, 
                "Submissions": {
                    "Attempts": "0"
                }, 
                "Takedowns": {
                    "Attempts": "2", 
                    "Landed": "0"
                }
            }, 
            "Strikes": {
                "Body Significant Strikes": {
                    "Attempts": "15", 
                    "Landed": "10"
                }, 
                "Body Total Strikes": {
                    "Attempts": "15", 
                    "Landed": "10"
                }, 
                "Clinch Body Strikes": {
                    "Attempts": "2", 
                    "Landed": "2"
                }, 
                "Clinch Head Strikes": {
                    "Attempts": "8", 
                    "Landed": "4"
                }, 
                "Clinch Leg Strikes": {
                    "Attempts": "1", 
                    "Landed": "1"
                }, 
                "Clinch Significant Kicks": {
                    "Attempts": "0", 
                    "Landed": "0"
                }, 
                "Clinch Significant Punches": {
                    "Attempts": "0", 
                    "Landed": "0"
                }, 
                "Clinch Significant Strikes": {
                    "Attempts": "8", 
                    "Landed": "6"
                }, 
                "Clinch Total Strikes": {
                    "Attempts": "11", 
                    "Landed": "7"
                }, 
                "Distance Body Kicks": {
                    "Attempts": "5", 
                    "Landed": "3"
                }, 
                "Distance Body Punches": {
                    "Attempts": "8", 
                    "Landed": "8"
                }, 
                "Distance Body Strikes": {
                    "Attempts": "13", 
                    "Landed": "8"
                }, 
                "Distance Head Kicks": {
                    "Attempts": "4", 
                    "Landed": "2"
                }, 
                "Distance Head Punches": {
                    "Attempts": "68", 
                    "Landed": "24"
                }, 
                "Distance Head Strikes": {
                    "Attempts": "95", 
                    "Landed": "30"
                }, 
                "Distance Leg Kicks": {
                    "Attempts": "10", 
                    "Landed": "8"
                }, 
                "Distance Leg Strikes": {
                    "Attempts": "20", 
                    "Landed": "14"
                }, 
                "Distance Strikes": {
                    "Attempts": "128", 
                    "Landed": "52"
                }, 
                "Ground Body Strikes": {
                    "Attempts": "0", 
                    "Landed": "0"
                }, 
                "Ground Head Strikes": {
                    "Attempts": "2", 
                    "Landed": "1"
                }, 
                "Ground Leg Strikes": {
                    "Attempts": "0", 
                    "Landed": "0"
                }, 
                "Ground Significant Kicks": {
                    "Attempts": "0", 
                    "Landed": "0"
                }, 
                "Ground Significant Punches": {
                    "Attempts": "1", 
                    "Landed": "1"
                }, 
                "Ground Significant Strikes": {
                    "Attempts": "2", 
                    "Landed": "1"
                }, 
                "Ground Total Strikes": {
                    "Attempts": "2", 
                    "Landed": "1"
                }, 
                "Head Significant Strikes": {
                    "Attempts": "103", 
                    "Landed": "35"
                }, 
                "Head Total Strikes": {
                    "Attempts": "105", 
                    "Landed": "35"
                }, 
                "Kicks": {
                    "Attempts": "19", 
                    "Landed": "13"
                }, 
                "Knock Down": {
                    "Landed": "1"
                }, 
                "Leg Total Strikes": {
                    "Attempts": "4", 
                    "Landed": "2"
                }, 
                "Legs Significant Strikes": {
                    "Attempts": "20", 
                    "Landed": "14"
                }, 
                "Legs Total Strikes": {
                    "Attempts": "17", 
                    "Landed": "13"
                }, 
                "Punches": {
                    "Attempts": "81", 
                    "Landed": "35"
                }, 
                "Significant Strikes": {
                    "Attempts": "138", 
                    "Landed": "59"
                }, 
                "Total Strikes": {
                    "Attempts": "141", 
                    "Landed": "60"
                }
            }, 
            "TIP": {
                "Back Control Time": "0.0", 
                "Clinch Time": "145.0", 
                "Control Time": "42.0", 
                "Distance Time": "738.0", 
                "Ground Control Time": "15.0", 
                "Ground Time": "17.0", 
                "Guard Control Time": "0.0", 
                "Half Guard Control Time": "0.0", 
                "Misc. Ground Control Time": "10.0", 
                "Mount Control Time": "5.0", 
                "Neutral Time": "748.0", 
                "Side Control Time": "0.0", 
                "Standing Time": "883.0"
            }
        }, 
        "Round3": {
            "Grappling": {
                "Reversals": {
                    "Landed": "0"
                }, 
                "Standups": {
                    "Landed": "0"
                }, 
                "Submissions": {
                    "Attempts": "0"
                }, 
                "Takedowns": {
                    "Attempts": "4", 
                    "Landed": "1"
                }
            }, 
            "Strikes": {
                "Body Significant Strikes": {
                    "Attempts": "8", 
                    "Landed": "5"
                }, 
                "Body Total Strikes": {
                    "Attempts": "10", 
                    "Landed": "7"
                }, 
                "Clinch Body Strikes": {
                    "Attempts": "3", 
                    "Landed": "2"
                }, 
                "Clinch Head Strikes": {
                    "Attempts": "1", 
                    "Landed": "0"
                }, 
                "Clinch Leg Strikes": {
                    "Attempts": "0", 
                    "Landed": "0"
                }, 
                "Clinch Significant Kicks": {
                    "Attempts": "1", 
                    "Landed": "0"
                }, 
                "Clinch Significant Punches": {
                    "Attempts": "0", 
                    "Landed": "0"
                }, 
                "Clinch Significant Strikes": {
                    "Attempts": "1", 
                    "Landed": "0"
                }, 
                "Clinch Total Strikes": {
                    "Attempts": "4", 
                    "Landed": "2"
                }, 
                "Distance Body Kicks": {
                    "Attempts": "2", 
                    "Landed": "2"
                }, 
                "Distance Body Punches": {
                    "Attempts": "0", 
                    "Landed": "0"
                }, 
                "Distance Body Strikes": {
                    "Attempts": "7", 
                    "Landed": "5"
                }, 
                "Distance Head Kicks": {
                    "Attempts": "2", 
                    "Landed": "0"
                }, 
                "Distance Head Punches": {
                    "Attempts": "58", 
                    "Landed": "15"
                }, 
                "Distance Head Strikes": {
                    "Attempts": "60", 
                    "Landed": "16"
                }, 
                "Distance Leg Kicks": {
                    "Attempts": "8", 
                    "Landed": "6"
                }, 
                "Distance Leg Strikes": {
                    "Attempts": "7", 
                    "Landed": "5"
                }, 
                "Distance Strikes": {
                    "Attempts": "74", 
                    "Landed": "26"
                }, 
                "Ground Body Strikes": {
                    "Attempts": "0", 
                    "Landed": "0"
                }, 
                "Ground Head Strikes": {
                    "Attempts": "6", 
                    "Landed": "6"
                }, 
                "Ground Leg Strikes": {
                    "Attempts": "0", 
                    "Landed": "0"
                }, 
                "Ground Significant Kicks": {
                    "Attempts": "0", 
                    "Landed": "0"
                }, 
                "Ground Significant Punches": {
                    "Attempts": "0", 
                    "Landed": "0"
                }, 
                "Ground Significant Strikes": {
                    "Attempts": "6", 
                    "Landed": "6"
                }, 
                "Ground Total Strikes": {
                    "Attempts": "6", 
                    "Landed": "6"
                }, 
                "Head Significant Strikes": {
                    "Attempts": "66", 
                    "Landed": "22"
                }, 
                "Head Total Strikes": {
                    "Attempts": "67", 
                    "Landed": "22"
                }, 
                "Kicks": {
                    "Attempts": "13", 
                    "Landed": "8"
                }, 
                "Knock Down": {
                    "Landed": "1"
                }, 
                "Leg Total Strikes": {
                    "Attempts": "4", 
                    "Landed": "2"
                }, 
                "Legs Significant Strikes": {
                    "Attempts": "7", 
                    "Landed": "5"
                }, 
                "Legs Total Strikes": {
                    "Attempts": "3", 
                    "Landed": "3"
                }, 
                "Punches": {
                    "Attempts": "61", 
                    "Landed": "17"
                }, 
                "Significant Strikes": {
                    "Attempts": "81", 
                    "Landed": "32"
                }, 
                "Total Strikes": {
                    "Attempts": "84", 
                    "Landed": "34"
                }
            }, 
            "TIP": {
                "Back Control Time": "0.0", 
                "Clinch Time": "109.0", 
                "Control Time": "109.0", 
                "Distance Time": "462.0", 
                "Ground Control Time": "37.0", 
                "Ground Time": "62.0", 
                "Guard Control Time": "15.0", 
                "Half Guard Control Time": "0.0", 
                "Misc. Ground Control Time": "14.0", 
                "Mount Control Time": "4.0", 
                "Neutral Time": "504.0", 
                "Side Control Time": "4.0", 
                "Standing Time": "571.0"
            }
        }, 
        "Round4": {
            "Grappling": {
                "Reversals": {
                    "Landed": "0"
                }, 
                "Standups": {
                    "Landed": "0"
                }, 
                "Submissions": {
                    "Attempts": "0"
                }, 
                "Takedowns": {
                    "Attempts": "1", 
                    "Landed": "0"
                }
            }, 
            "Strikes": {
                "Body Significant Strikes": {
                    "Attempts": "1", 
                    "Landed": "1"
                }, 
                "Body Total Strikes": {
                    "Attempts": "3", 
                    "Landed": "3"
                }, 
                "Clinch Body Strikes": {
                    "Attempts": "2", 
                    "Landed": "2"
                }, 
                "Clinch Head Strikes": {
                    "Attempts": "0", 
                    "Landed": "0"
                }, 
                "Clinch Leg Strikes": {
                    "Attempts": "5", 
                    "Landed": "5"
                }, 
                "Clinch Significant Kicks": {
                    "Attempts": "0", 
                    "Landed": "0"
                }, 
                "Clinch Significant Punches": {
                    "Attempts": "0", 
                    "Landed": "0"
                }, 
                "Clinch Significant Strikes": {
                    "Attempts": "0", 
                    "Landed": "0"
                }, 
                "Clinch Total Strikes": {
                    "Attempts": "7", 
                    "Landed": "7"
                }, 
                "Distance Body Kicks": {
                    "Attempts": "0", 
                    "Landed": "0"
                }, 
                "Distance Body Punches": {
                    "Attempts": "1", 
                    "Landed": "1"
                }, 
                "Distance Body Strikes": {
                    "Attempts": "1", 
                    "Landed": "1"
                }, 
                "Distance Head Kicks": {
                    "Attempts": "1", 
                    "Landed": "0"
                }, 
                "Distance Head Punches": {
                    "Attempts": "35", 
                    "Landed": "13"
                }, 
                "Distance Head Strikes": {
                    "Attempts": "36", 
                    "Landed": "13"
                }, 
                "Distance Leg Kicks": {
                    "Attempts": "2", 
                    "Landed": "1"
                }, 
                "Distance Leg Strikes": {
                    "Attempts": "3", 
                    "Landed": "2"
                }, 
                "Distance Strikes": {
                    "Attempts": "40", 
                    "Landed": "16"
                }, 
                "Ground Body Strikes": {
                    "Attempts": "0", 
                    "Landed": "0"
                }, 
                "Ground Head Strikes": {
                    "Attempts": "0", 
                    "Landed": "0"
                }, 
                "Ground Leg Strikes": {
                    "Attempts": "0", 
                    "Landed": "0"
                }, 
                "Ground Significant Kicks": {
                    "Attempts": "0", 
                    "Landed": "0"
                }, 
                "Ground Significant Punches": {
                    "Attempts": "0", 
                    "Landed": "0"
                }, 
                "Ground Significant Strikes": {
                    "Attempts": "0", 
                    "Landed": "0"
                }, 
                "Ground Total Strikes": {
                    "Attempts": "0", 
                    "Landed": "0"
                }, 
                "Head Significant Strikes": {
                    "Attempts": "36", 
                    "Landed": "13"
                }, 
                "Head Total Strikes": {
                    "Attempts": "36", 
                    "Landed": "13"
                }, 
                "Kicks": {
                    "Attempts": "3", 
                    "Landed": "1"
                }, 
                "Knock Down": {
                    "Landed": "0"
                }, 
                "Leg Total Strikes": {
                    "Attempts": "", 
                    "Landed": ""
                }, 
                "Legs Significant Strikes": {
                    "Attempts": "3", 
                    "Landed": "2"
                }, 
                "Legs Total Strikes": {
                    "Attempts": "8", 
                    "Landed": "7"
                }, 
                "Punches": {
                    "Attempts": "44", 
                    "Landed": "22"
                }, 
                "Significant Strikes": {
                    "Attempts": "40", 
                    "Landed": "16"
                }, 
                "Total Strikes": {
                    "Attempts": "47", 
                    "Landed": "23"
                }
            }, 
            "TIP": {
                "Back Control Time": "0.0", 
                "Clinch Time": "67.0", 
                "Control Time": "56.0", 
                "Distance Time": "232.0", 
                "Ground Control Time": "0.0", 
                "Ground Time": "0.0", 
                "Guard Control Time": "0.0", 
                "Half Guard Control Time": "0.0", 
                "Misc. Ground Control Time": "0.0", 
                "Mount Control Time": "0.0", 
                "Neutral Time": "232.0", 
                "Side Control Time": "0.0", 
                "Standing Time": "299.0"
            }
        }, 
        "Round5": {
            "Grappling": {
                "Reversals": {
                    "Landed": "0"
                }, 
                "Standups": {
                    "Landed": "0"
                }, 
                "Submissions": {
                    "Attempts": "0"
                }, 
                "Takedowns": {
                    "Attempts": "0", 
                    "Landed": "0"
                }
            }, 
            "Strikes": {
                "Body Significant Strikes": {
                    "Attempts": "4", 
                    "Landed": "1"
                }, 
                "Body Total Strikes": {
                    "Attempts": "4", 
                    "Landed": "1"
                }, 
                "Clinch Body Strikes": {
                    "Attempts": "0", 
                    "Landed": "0"
                }, 
                "Clinch Head Strikes": {
                    "Attempts": "0", 
                    "Landed": "0"
                }, 
                "Clinch Leg Strikes": {
                    "Attempts": "0", 
                    "Landed": "0"
                }, 
                "Clinch Significant Kicks": {
                    "Attempts": "0", 
                    "Landed": "0"
                }, 
                "Clinch Significant Punches": {
                    "Attempts": "0", 
                    "Landed": "0"
                }, 
                "Clinch Significant Strikes": {
                    "Attempts": "0", 
                    "Landed": "0"
                }, 
                "Clinch Total Strikes": {
                    "Attempts": "0", 
                    "Landed": "0"
                }, 
                "Distance Body Kicks": {
                    "Attempts": "2", 
                    "Landed": "0"
                }, 
                "Distance Body Punches": {
                    "Attempts": "2", 
                    "Landed": "1"
                }, 
                "Distance Body Strikes": {
                    "Attempts": "4", 
                    "Landed": "1"
                }, 
                "Distance Head Kicks": {
                    "Attempts": "0", 
                    "Landed": "0"
                }, 
                "Distance Head Punches": {
                    "Attempts": "89", 
                    "Landed": "28"
                }, 
                "Distance Head Strikes": {
                    "Attempts": "89", 
                    "Landed": "28"
                }, 
                "Distance Leg Kicks": {
                    "Attempts": "2", 
                    "Landed": "2"
                }, 
                "Distance Leg Strikes": {
                    "Attempts": "3", 
                    "Landed": "3"
                }, 
                "Distance Strikes": {
                    "Attempts": "96", 
                    "Landed": "32"
                }, 
                "Ground Body Strikes": {
                    "Attempts": "0", 
                    "Landed": "0"
                }, 
                "Ground Head Strikes": {
                    "Attempts": "0", 
                    "Landed": "0"
                }, 
                "Ground Leg Strikes": {
                    "Attempts": "0", 
                    "Landed": "0"
                }, 
                "Ground Significant Kicks": {
                    "Attempts": "0", 
                    "Landed": "0"
                }, 
                "Ground Significant Punches": {
                    "Attempts": "0", 
                    "Landed": "0"
                }, 
                "Ground Significant Strikes": {
                    "Attempts": "0", 
                    "Landed": "0"
                }, 
                "Ground Total Strikes": {
                    "Attempts": "0", 
                    "Landed": "0"
                }, 
                "Head Significant Strikes": {
                    "Attempts": "89", 
                    "Landed": "28"
                }, 
                "Head Total Strikes": {
                    "Attempts": "89", 
                    "Landed": "28"
                }, 
                "Kicks": {
                    "Attempts": "4", 
                    "Landed": "2"
                }, 
                "Knock Down": {
                    "Landed": "0"
                }, 
                "Leg Total Strikes": {
                    "Attempts": "", 
                    "Landed": ""
                }, 
                "Legs Significant Strikes": {
                    "Attempts": "3", 
                    "Landed": "3"
                }, 
                "Legs Total Strikes": {
                    "Attempts": "3", 
                    "Landed": "3"
                }, 
                "Punches": {
                    "Attempts": "92", 
                    "Landed": "30"
                }, 
                "Significant Strikes": {
                    "Attempts": "96", 
                    "Landed": "32"
                }, 
                "Total Strikes": {
                    "Attempts": "96", 
                    "Landed": "32"
                }
            }, 
            "TIP": {
                "Back Control Time": "0.0", 
                "Clinch Time": "0.0", 
                "Control Time": "0.0", 
                "Distance Time": "300.0", 
                "Ground Control Time": "0.0", 
                "Ground Time": "0.0", 
                "Guard Control Time": "0.0", 
                "Half Guard Control Time": "0.0", 
                "Misc. Ground Control Time": "0.0", 
                "Mount Control Time": "0.0", 
                "Neutral Time": "300.0", 
                "Side Control Time": "0.0", 
                "Standing Time": "300.0"
            }
        }
    }, 
    "Record": [
        1, 
        0, 
        1
    ]
}