{"Timestamp": "05:37:47 03/23/2015", "FMLiveFeed": {"EventID": "713", "Status": "official", "RoundStats": {"Round2": {"Blue": {"Grappling": {"Reversals": {"Landed": ""}, "Submissions": {"Attempts": "0"}, "Takedowns": {"Landed": "0", "Attempts": "1"}, "Standups": {"Landed": "0"}}, "TIP": {"Guard Control Time": "00:00", "Ground Time": "00:34", "Half Guard Control Time": "00:00", "Standing Time": "01:24", "Mount Control Time": "00:00", "Side Control Time": "00:00", "Ground Control Time": "00:00", "Misc. Ground Control Time": "00:00", "Distance Time": "01:16", "Control Time": "00:00", "Clinch Time": "00:08", "Neutral Time": "01:24", "Back Control Time": "00:00"}, "FighterID": "2159", "Strikes": {"Distance Leg Strikes": {"Landed": "2", "Attempts": "2"}, "Knock Down": {"Landed": "0"}, "Ground Leg Strikes": {"Landed": "0", "Attempts": "0"}, "Clinch Body Strikes": {"Landed": "0", "Attempts": "0"}, "Ground Significant Punches": {"Landed": "", "Attempts": ""}, "Ground Total Strikes": {"Landed": "0", "Attempts": "0"}, "Head Total Strikes": {"Landed": "3", "Attempts": "9"}, "Ground Head Strikes": {"Landed": "0", "Attempts": "0"}, "Distance Head Punches": {"Landed": "", "Attempts": ""}, "Distance Body Punches": {"Landed": "", "Attempts": ""}, "Distance Body Kicks": {"Landed": "", "Attempts": ""}, "Clinch Head Strikes": {"Landed": "0", "Attempts": "0"}, "Kicks": {"Landed": "", "Attempts": ""}, "Body Total Strikes": {"Landed": "0", "Attempts": "0"}, "Total Strikes": {"Landed": "5", "Attempts": "11"}, "Distance Body Strikes": {"Landed": "0", "Attempts": "0"}, "Clinch Significant Strikes": {"Landed": "0", "Attempts": "0"}, "Ground Body Strikes": {"Landed": "0", "Attempts": "0"}, "Legs Significant Strikes": {"Landed": "2", "Attempts": "2"}, "Ground Significant Kicks": {"Landed": "", "Attempts": ""}, "Distance Strikes": {"Landed": "5", "Attempts": "11"}, "Clinch Total Strikes": {"Landed": "0", "Attempts": "0"}, "Clinch Leg Strikes": {"Landed": "0", "Attempts": "0"}, "Punches": {"Landed": "", "Attempts": ""}, "Legs Total Strikes": {"Landed": "2", "Attempts": "2"}, "Ground Significant Strikes": {"Landed": "0", "Attempts": "0"}, "Clinch Significant Punches": {"Landed": "", "Attempts": ""}, "Significant Strikes": {"Landed": "5", "Attempts": "11"}, "Body Significant Strikes": {"Landed": "0", "Attempts": "0"}, "Distance Head Strikes": {"Landed": "3", "Attempts": "9"}, "Distance Leg Kicks": {"Landed": "", "Attempts": ""}, "Distance Head Kicks": {"Landed": "", "Attempts": ""}, "Head Significant Strikes": {"Landed": "3", "Attempts": "9"}, "Clinch Significant Kicks": {"Landed": "", "Attempts": ""}}}, "Red": {"Grappling": {"Reversals": {"Landed": ""}, "Submissions": {"Attempts": "1"}, "Takedowns": {"Landed": "1", "Attempts": "1"}, "Standups": {"Landed": "0"}}, "TIP": {"Guard Control Time": "00:09", "Ground Time": "00:34", "Half Guard Control Time": "00:00", "Standing Time": "01:24", "Mount Control Time": "00:24", "Side Control Time": "00:01", "Ground Control Time": "00:34", "Misc. Ground Control Time": "00:00", "Distance Time": "01:16", "Control Time": "00:34", "Clinch Time": "00:08", "Neutral Time": "01:24", "Back Control Time": "00:00"}, "FighterID": "2078", "Strikes": {"Distance Leg Strikes": {"Landed": "3", "Attempts": "5"}, "Knock Down": {"Landed": "0"}, "Ground Leg Strikes": {"Landed": "0", "Attempts": "0"}, "Clinch Body Strikes": {"Landed": "0", "Attempts": "0"}, "Ground Significant Punches": {"Landed": "", "Attempts": ""}, "Ground Total Strikes": {"Landed": "1", "Attempts": "1"}, "Head Total Strikes": {"Landed": "5", "Attempts": "12"}, "Ground Head Strikes": {"Landed": "0", "Attempts": "0"}, "Distance Head Punches": {"Landed": "", "Attempts": ""}, "Distance Body Punches": {"Landed": "", "Attempts": ""}, "Distance Body Kicks": {"Landed": "", "Attempts": ""}, "Clinch Head Strikes": {"Landed": "0", "Attempts": "0"}, "Kicks": {"Landed": "", "Attempts": ""}, "Body Total Strikes": {"Landed": "0", "Attempts": "0"}, "Total Strikes": {"Landed": "8", "Attempts": "17"}, "Distance Body Strikes": {"Landed": "0", "Attempts": "0"}, "Clinch Significant Strikes": {"Landed": "0", "Attempts": "0"}, "Ground Body Strikes": {"Landed": "0", "Attempts": "0"}, "Legs Significant Strikes": {"Landed": "3", "Attempts": "5"}, "Ground Significant Kicks": {"Landed": "", "Attempts": ""}, "Distance Strikes": {"Landed": "7", "Attempts": "16"}, "Clinch Total Strikes": {"Landed": "0", "Attempts": "0"}, "Clinch Leg Strikes": {"Landed": "0", "Attempts": "0"}, "Punches": {"Landed": "", "Attempts": ""}, "Legs Total Strikes": {"Landed": "3", "Attempts": "5"}, "Ground Significant Strikes": {"Landed": "0", "Attempts": "0"}, "Clinch Significant Punches": {"Landed": "", "Attempts": ""}, "Significant Strikes": {"Landed": "7", "Attempts": "16"}, "Body Significant Strikes": {"Landed": "0", "Attempts": "0"}, "Distance Head Strikes": {"Landed": "4", "Attempts": "11"}, "Distance Leg Kicks": {"Landed": "", "Attempts": ""}, "Distance Head Kicks": {"Landed": "", "Attempts": ""}, "Head Significant Strikes": {"Landed": "4", "Attempts": "11"}, "Clinch Significant Kicks": {"Landed": "", "Attempts": ""}}}}, "Round1": {"Blue": {"Grappling": {"Reversals": {"Landed": ""}, "Submissions": {"Attempts": "0"}, "Takedowns": {"Landed": "0", "Attempts": "2"}, "Standups": {"Landed": "0"}}, "TIP": {"Guard Control Time": "00:00", "Ground Time": "00:12", "Half Guard Control Time": "00:00", "Standing Time": "04:46", "Mount Control Time": "00:12", "Side Control Time": "00:00", "Ground Control Time": "00:12", "Misc. Ground Control Time": "00:00", "Distance Time": "02:44", "Control Time": "01:59", "Clinch Time": "02:02", "Neutral Time": "02:49", "Back Control Time": "00:00"}, "FighterID": "2159", "Strikes": {"Distance Leg Strikes": {"Landed": "3", "Attempts": "3"}, "Knock Down": {"Landed": "0"}, "Ground Leg Strikes": {"Landed": "0", "Attempts": "0"}, "Clinch Body Strikes": {"Landed": "0", "Attempts": "0"}, "Ground Significant Punches": {"Landed": "", "Attempts": ""}, "Ground Total Strikes": {"Landed": "0", "Attempts": "0"}, "Head Total Strikes": {"Landed": "5", "Attempts": "21"}, "Ground Head Strikes": {"Landed": "0", "Attempts": "0"}, "Distance Head Punches": {"Landed": "", "Attempts": ""}, "Distance Body Punches": {"Landed": "", "Attempts": ""}, "Distance Body Kicks": {"Landed": "", "Attempts": ""}, "Clinch Head Strikes": {"Landed": "0", "Attempts": "0"}, "Kicks": {"Landed": "", "Attempts": ""}, "Body Total Strikes": {"Landed": "1", "Attempts": "1"}, "Total Strikes": {"Landed": "19", "Attempts": "35"}, "Distance Body Strikes": {"Landed": "1", "Attempts": "1"}, "Clinch Significant Strikes": {"Landed": "0", "Attempts": "0"}, "Ground Body Strikes": {"Landed": "0", "Attempts": "0"}, "Legs Significant Strikes": {"Landed": "3", "Attempts": "3"}, "Ground Significant Kicks": {"Landed": "", "Attempts": ""}, "Distance Strikes": {"Landed": "9", "Attempts": "25"}, "Clinch Total Strikes": {"Landed": "10", "Attempts": "10"}, "Clinch Leg Strikes": {"Landed": "0", "Attempts": "0"}, "Punches": {"Landed": "", "Attempts": ""}, "Legs Total Strikes": {"Landed": "13", "Attempts": "13"}, "Ground Significant Strikes": {"Landed": "0", "Attempts": "0"}, "Clinch Significant Punches": {"Landed": "", "Attempts": ""}, "Significant Strikes": {"Landed": "9", "Attempts": "25"}, "Body Significant Strikes": {"Landed": "1", "Attempts": "1"}, "Distance Head Strikes": {"Landed": "5", "Attempts": "21"}, "Distance Leg Kicks": {"Landed": "", "Attempts": ""}, "Distance Head Kicks": {"Landed": "", "Attempts": ""}, "Head Significant Strikes": {"Landed": "5", "Attempts": "21"}, "Clinch Significant Kicks": {"Landed": "", "Attempts": ""}}}, "Red": {"Grappling": {"Reversals": {"Landed": ""}, "Submissions": {"Attempts": "0"}, "Takedowns": {"Landed": "0", "Attempts": "1"}, "Standups": {"Landed": "0"}}, "TIP": {"Guard Control Time": "00:00", "Ground Time": "00:12", "Half Guard Control Time": "00:00", "Standing Time": "04:46", "Mount Control Time": "00:00", "Side Control Time": "00:00", "Ground Control Time": "00:00", "Misc. Ground Control Time": "00:00", "Distance Time": "02:44", "Control Time": "00:10", "Clinch Time": "02:02", "Neutral Time": "02:49", "Back Control Time": "00:00"}, "FighterID": "2078", "Strikes": {"Distance Leg Strikes": {"Landed": "3", "Attempts": "6"}, "Knock Down": {"Landed": "0"}, "Ground Leg Strikes": {"Landed": "0", "Attempts": "0"}, "Clinch Body Strikes": {"Landed": "0", "Attempts": "0"}, "Ground Significant Punches": {"Landed": "", "Attempts": ""}, "Ground Total Strikes": {"Landed": "0", "Attempts": "0"}, "Head Total Strikes": {"Landed": "3", "Attempts": "15"}, "Ground Head Strikes": {"Landed": "0", "Attempts": "0"}, "Distance Head Punches": {"Landed": "", "Attempts": ""}, "Distance Body Punches": {"Landed": "", "Attempts": ""}, "Distance Body Kicks": {"Landed": "", "Attempts": ""}, "Clinch Head Strikes": {"Landed": "0", "Attempts": "0"}, "Kicks": {"Landed": "", "Attempts": ""}, "Body Total Strikes": {"Landed": "1", "Attempts": "4"}, "Total Strikes": {"Landed": "8", "Attempts": "26"}, "Distance Body Strikes": {"Landed": "0", "Attempts": "3"}, "Clinch Significant Strikes": {"Landed": "0", "Attempts": "0"}, "Ground Body Strikes": {"Landed": "0", "Attempts": "0"}, "Legs Significant Strikes": {"Landed": "3", "Attempts": "6"}, "Ground Significant Kicks": {"Landed": "", "Attempts": ""}, "Distance Strikes": {"Landed": "5", "Attempts": "23"}, "Clinch Total Strikes": {"Landed": "3", "Attempts": "3"}, "Clinch Leg Strikes": {"Landed": "0", "Attempts": "0"}, "Punches": {"Landed": "", "Attempts": ""}, "Legs Total Strikes": {"Landed": "4", "Attempts": "7"}, "Ground Significant Strikes": {"Landed": "0", "Attempts": "0"}, "Clinch Significant Punches": {"Landed": "", "Attempts": ""}, "Significant Strikes": {"Landed": "5", "Attempts": "23"}, "Body Significant Strikes": {"Landed": "0", "Attempts": "3"}, "Distance Head Strikes": {"Landed": "2", "Attempts": "14"}, "Distance Leg Kicks": {"Landed": "", "Attempts": ""}, "Distance Head Kicks": {"Landed": "", "Attempts": ""}, "Head Significant Strikes": {"Landed": "2", "Attempts": "14"}, "Clinch Significant Kicks": {"Landed": "", "Attempts": ""}}}}}, "Accolade": "", "CurrentRound": "2", "FightID": "5275", "MaxRounds": "3", "FightStats": {"Blue": {"Grappling": {"Reversals": {"Landed": ""}, "Submissions": {"Attempts": "0"}, "Takedowns": {"Landed": "0", "Attempts": "3"}, "Standups": {"Landed": "0"}}, "TIP": {"Guard Control Time": "00:00", "Ground Time": "00:46", "Half Guard Control Time": "00:00", "Standing Time": "06:10", "Mount Control Time": "00:12", "Side Control Time": "00:00", "Ground Control Time": "00:12", "Misc. Ground Control Time": "00:00", "Distance Time": "04:00", "Control Time": "01:59", "Clinch Time": "02:10", "Neutral Time": "04:13", "Back Control Time": "00:00"}, "FighterID": "2159", "Strikes": {"Distance Leg Strikes": {"Landed": "5", "Attempts": "5"}, "Knock Down": {"Landed": "0"}, "Ground Leg Strikes": {"Landed": "0", "Attempts": "0"}, "Clinch Body Strikes": {"Landed": "0", "Attempts": "0"}, "Ground Significant Punches": {"Landed": "", "Attempts": ""}, "Ground Total Strikes": {"Landed": "0", "Attempts": "0"}, "Head Total Strikes": {"Landed": "8", "Attempts": "30"}, "Ground Head Strikes": {"Landed": "0", "Attempts": "0"}, "Distance Head Punches": {"Landed": "", "Attempts": ""}, "Distance Body Punches": {"Landed": "", "Attempts": ""}, "Distance Body Kicks": {"Landed": "", "Attempts": ""}, "Clinch Head Strikes": {"Landed": "0", "Attempts": "0"}, "Kicks": {"Landed": "", "Attempts": ""}, "Body Total Strikes": {"Landed": "1", "Attempts": "1"}, "Total Strikes": {"Landed": "24", "Attempts": "46"}, "Distance Body Strikes": {"Landed": "1", "Attempts": "1"}, "Clinch Significant Strikes": {"Landed": "0", "Attempts": "0"}, "Ground Body Strikes": {"Landed": "0", "Attempts": "0"}, "Legs Significant Strikes": {"Landed": "5", "Attempts": "5"}, "Ground Significant Kicks": {"Landed": "", "Attempts": ""}, "Distance Strikes": {"Landed": "14", "Attempts": "36"}, "Clinch Total Strikes": {"Landed": "10", "Attempts": "10"}, "Clinch Leg Strikes": {"Landed": "0", "Attempts": "0"}, "Punches": {"Landed": "", "Attempts": ""}, "Legs Total Strikes": {"Landed": "15", "Attempts": "15"}, "Ground Significant Strikes": {"Landed": "0", "Attempts": "0"}, "Clinch Significant Punches": {"Landed": "", "Attempts": ""}, "Significant Strikes": {"Landed": "14", "Attempts": "36"}, "Body Significant Strikes": {"Landed": "1", "Attempts": "1"}, "Distance Head Strikes": {"Landed": "8", "Attempts": "30"}, "Distance Leg Kicks": {"Landed": "", "Attempts": ""}, "Distance Head Kicks": {"Landed": "", "Attempts": ""}, "Head Significant Strikes": {"Landed": "8", "Attempts": "30"}, "Clinch Significant Kicks": {"Landed": "", "Attempts": ""}}}, "Red": {"Grappling": {"Reversals": {"Landed": ""}, "Submissions": {"Attempts": "1"}, "Takedowns": {"Landed": "1", "Attempts": "2"}, "Standups": {"Landed": "0"}}, "TIP": {"Guard Control Time": "00:09", "Ground Time": "00:46", "Half Guard Control Time": "00:00", "Standing Time": "06:10", "Mount Control Time": "00:24", "Side Control Time": "00:01", "Ground Control Time": "00:34", "Misc. Ground Control Time": "00:00", "Distance Time": "04:00", "Control Time": "00:44", "Clinch Time": "02:10", "Neutral Time": "04:13", "Back Control Time": "00:00"}, "FighterID": "2078", "Strikes": {"Distance Leg Strikes": {"Landed": "6", "Attempts": "11"}, "Knock Down": {"Landed": "0"}, "Ground Leg Strikes": {"Landed": "0", "Attempts": "0"}, "Clinch Body Strikes": {"Landed": "0", "Attempts": "0"}, "Ground Significant Punches": {"Landed": "", "Attempts": ""}, "Ground Total Strikes": {"Landed": "1", "Attempts": "1"}, "Head Total Strikes": {"Landed": "8", "Attempts": "27"}, "Ground Head Strikes": {"Landed": "0", "Attempts": "0"}, "Distance Head Punches": {"Landed": "", "Attempts": ""}, "Distance Body Punches": {"Landed": "", "Attempts": ""}, "Distance Body Kicks": {"Landed": "", "Attempts": ""}, "Clinch Head Strikes": {"Landed": "0", "Attempts": "0"}, "Kicks": {"Landed": "", "Attempts": ""}, "Body Total Strikes": {"Landed": "1", "Attempts": "4"}, "Total Strikes": {"Landed": "16", "Attempts": "43"}, "Distance Body Strikes": {"Landed": "0", "Attempts": "3"}, "Clinch Significant Strikes": {"Landed": "0", "Attempts": "0"}, "Ground Body Strikes": {"Landed": "0", "Attempts": "0"}, "Legs Significant Strikes": {"Landed": "6", "Attempts": "11"}, "Ground Significant Kicks": {"Landed": "", "Attempts": ""}, "Distance Strikes": {"Landed": "12", "Attempts": "39"}, "Clinch Total Strikes": {"Landed": "3", "Attempts": "3"}, "Clinch Leg Strikes": {"Landed": "0", "Attempts": "0"}, "Punches": {"Landed": "", "Attempts": ""}, "Legs Total Strikes": {"Landed": "7", "Attempts": "12"}, "Ground Significant Strikes": {"Landed": "0", "Attempts": "0"}, "Clinch Significant Punches": {"Landed": "", "Attempts": ""}, "Significant Strikes": {"Landed": "12", "Attempts": "39"}, "Body Significant Strikes": {"Landed": "0", "Attempts": "3"}, "Distance Head Strikes": {"Landed": "6", "Attempts": "25"}, "Distance Leg Kicks": {"Landed": "", "Attempts": ""}, "Distance Head Kicks": {"Landed": "", "Attempts": ""}, "Head Significant Strikes": {"Landed": "6", "Attempts": "25"}, "Clinch Significant Kicks": {"Landed": "", "Attempts": ""}}}}, "Fighters": {"Blue": {"Name": "Tony Martin", "FighterID": "2159"}, "Red": {"Name": "Leonardo Santos", "FighterID": "2078"}}, "Referee": "John McCarthy", "WeightClass": "Lightweight"}, "Type": "Stats"}