{"Timestamp": "04:32:44 11/27/2016", "FMLiveFeed": {"EventID": "797", "Status": "official", "RoundStats": {"Round2": {"Blue": {"Grappling": {"Reversals": {"Landed": "0"}, "Submissions": {"Attempts": "0"}, "Takedowns": {"Landed": "1", "Attempts": "1"}, "Standups": {"Landed": "0"}}, "TIP": {"Guard Control Time": "00:57", "Ground Time": "01:48", "Half Guard Control Time": "00:26", "Standing Time": "00:18", "Mount Control Time": "00:25", "Side Control Time": "00:00", "Ground Control Time": "01:48", "Misc. Ground Control Time": "00:00", "Distance Time": "00:18", "Control Time": "01:48", "Clinch Time": "00:00", "Neutral Time": "00:18", "Back Control Time": "00:00"}, "FighterID": "2824", "Strikes": {"Distance Leg Strikes": {"Landed": "1", "Attempts": "1"}, "Knock Down": {"Landed": "0"}, "Ground Leg Strikes": {"Landed": "0", "Attempts": "0"}, "Clinch Body Strikes": {"Landed": "0", "Attempts": "0"}, "Ground Significant Punches": {"Landed": "", "Attempts": ""}, "Ground Total Strikes": {"Landed": "32", "Attempts": "45"}, "Head Total Strikes": {"Landed": "32", "Attempts": "46"}, "Ground Head Strikes": {"Landed": "30", "Attempts": "43"}, "Distance Head Punches": {"Landed": "", "Attempts": ""}, "Distance Body Punches": {"Landed": "", "Attempts": ""}, "Distance Body Kicks": {"Landed": "", "Attempts": ""}, "Clinch Head Strikes": {"Landed": "0", "Attempts": "0"}, "Kicks": {"Landed": "", "Attempts": ""}, "Body Total Strikes": {"Landed": "0", "Attempts": "0"}, "Total Strikes": {"Landed": "33", "Attempts": "47"}, "Distance Body Strikes": {"Landed": "0", "Attempts": "0"}, "Clinch Significant Strikes": {"Landed": "0", "Attempts": "0"}, "Ground Body Strikes": {"Landed": "0", "Attempts": "0"}, "Legs Significant Strikes": {"Landed": "1", "Attempts": "1"}, "Ground Significant Kicks": {"Landed": "", "Attempts": ""}, "Distance Strikes": {"Landed": "1", "Attempts": "2"}, "Clinch Total Strikes": {"Landed": "0", "Attempts": "0"}, "Clinch Leg Strikes": {"Landed": "0", "Attempts": "0"}, "Punches": {"Landed": "", "Attempts": ""}, "Legs Total Strikes": {"Landed": "1", "Attempts": "1"}, "Ground Significant Strikes": {"Landed": "30", "Attempts": "43"}, "Clinch Significant Punches": {"Landed": "", "Attempts": ""}, "Significant Strikes": {"Landed": "31", "Attempts": "45"}, "Body Significant Strikes": {"Landed": "0", "Attempts": "0"}, "Distance Head Strikes": {"Landed": "0", "Attempts": "1"}, "Distance Leg Kicks": {"Landed": "", "Attempts": ""}, "Distance Head Kicks": {"Landed": "", "Attempts": ""}, "Head Significant Strikes": {"Landed": "30", "Attempts": "44"}, "Clinch Significant Kicks": {"Landed": "", "Attempts": ""}}}, "Red": {"Grappling": {"Reversals": {"Landed": "0"}, "Submissions": {"Attempts": "0"}, "Takedowns": {"Landed": "0", "Attempts": "0"}, "Standups": {"Landed": "0"}}, "TIP": {"Guard Control Time": "00:00", "Ground Time": "01:48", "Half Guard Control Time": "00:00", "Standing Time": "00:18", "Mount Control Time": "00:00", "Side Control Time": "00:00", "Ground Control Time": "00:00", "Misc. Ground Control Time": "00:00", "Distance Time": "00:18", "Control Time": "00:00", "Clinch Time": "00:00", "Neutral Time": "00:18", "Back Control Time": "00:00"}, "FighterID": "2626", "Strikes": {"Distance Leg Strikes": {"Landed": "0", "Attempts": "0"}, "Knock Down": {"Landed": "0"}, "Ground Leg Strikes": {"Landed": "0", "Attempts": "0"}, "Clinch Body Strikes": {"Landed": "0", "Attempts": "0"}, "Ground Significant Punches": {"Landed": "", "Attempts": ""}, "Ground Total Strikes": {"Landed": "0", "Attempts": "0"}, "Head Total Strikes": {"Landed": "1", "Attempts": "4"}, "Ground Head Strikes": {"Landed": "0", "Attempts": "0"}, "Distance Head Punches": {"Landed": "", "Attempts": ""}, "Distance Body Punches": {"Landed": "", "Attempts": ""}, "Distance Body Kicks": {"Landed": "", "Attempts": ""}, "Clinch Head Strikes": {"Landed": "0", "Attempts": "0"}, "Kicks": {"Landed": "", "Attempts": ""}, "Body Total Strikes": {"Landed": "0", "Attempts": "0"}, "Total Strikes": {"Landed": "1", "Attempts": "4"}, "Distance Body Strikes": {"Landed": "0", "Attempts": "0"}, "Clinch Significant Strikes": {"Landed": "0", "Attempts": "0"}, "Ground Body Strikes": {"Landed": "0", "Attempts": "0"}, "Legs Significant Strikes": {"Landed": "0", "Attempts": "0"}, "Ground Significant Kicks": {"Landed": "", "Attempts": ""}, "Distance Strikes": {"Landed": "1", "Attempts": "4"}, "Clinch Total Strikes": {"Landed": "0", "Attempts": "0"}, "Clinch Leg Strikes": {"Landed": "0", "Attempts": "0"}, "Punches": {"Landed": "", "Attempts": ""}, "Legs Total Strikes": {"Landed": "0", "Attempts": "0"}, "Ground Significant Strikes": {"Landed": "0", "Attempts": "0"}, "Clinch Significant Punches": {"Landed": "", "Attempts": ""}, "Significant Strikes": {"Landed": "1", "Attempts": "4"}, "Body Significant Strikes": {"Landed": "0", "Attempts": "0"}, "Distance Head Strikes": {"Landed": "1", "Attempts": "4"}, "Distance Leg Kicks": {"Landed": "", "Attempts": ""}, "Distance Head Kicks": {"Landed": "", "Attempts": ""}, "Head Significant Strikes": {"Landed": "1", "Attempts": "4"}, "Clinch Significant Kicks": {"Landed": "", "Attempts": ""}}}}, "Round1": {"Blue": {"Grappling": {"Reversals": {"Landed": "1"}, "Submissions": {"Attempts": "0"}, "Takedowns": {"Landed": "2", "Attempts": "2"}, "Standups": {"Landed": "1"}}, "TIP": {"Guard Control Time": "00:12", "Ground Time": "03:36", "Half Guard Control Time": "01:03", "Standing Time": "01:43", "Mount Control Time": "00:34", "Side Control Time": "00:00", "Ground Control Time": "01:49", "Misc. Ground Control Time": "00:00", "Distance Time": "00:35", "Control Time": "02:41", "Clinch Time": "01:08", "Neutral Time": "00:46", "Back Control Time": "00:00"}, "FighterID": "2824", "Strikes": {"Distance Leg Strikes": {"Landed": "0", "Attempts": "1"}, "Knock Down": {"Landed": "0"}, "Ground Leg Strikes": {"Landed": "0", "Attempts": "0"}, "Clinch Body Strikes": {"Landed": "2", "Attempts": "2"}, "Ground Significant Punches": {"Landed": "", "Attempts": ""}, "Ground Total Strikes": {"Landed": "16", "Attempts": "24"}, "Head Total Strikes": {"Landed": "18", "Attempts": "28"}, "Ground Head Strikes": {"Landed": "15", "Attempts": "22"}, "Distance Head Punches": {"Landed": "", "Attempts": ""}, "Distance Body Punches": {"Landed": "", "Attempts": ""}, "Distance Body Kicks": {"Landed": "", "Attempts": ""}, "Clinch Head Strikes": {"Landed": "1", "Attempts": "1"}, "Kicks": {"Landed": "", "Attempts": ""}, "Body Total Strikes": {"Landed": "2", "Attempts": "3"}, "Total Strikes": {"Landed": "22", "Attempts": "34"}, "Distance Body Strikes": {"Landed": "0", "Attempts": "0"}, "Clinch Significant Strikes": {"Landed": "3", "Attempts": "3"}, "Ground Body Strikes": {"Landed": "0", "Attempts": "1"}, "Legs Significant Strikes": {"Landed": "0", "Attempts": "1"}, "Ground Significant Kicks": {"Landed": "", "Attempts": ""}, "Distance Strikes": {"Landed": "1", "Attempts": "5"}, "Clinch Total Strikes": {"Landed": "5", "Attempts": "5"}, "Clinch Leg Strikes": {"Landed": "0", "Attempts": "0"}, "Punches": {"Landed": "", "Attempts": ""}, "Legs Total Strikes": {"Landed": "2", "Attempts": "3"}, "Ground Significant Strikes": {"Landed": "15", "Attempts": "23"}, "Clinch Significant Punches": {"Landed": "", "Attempts": ""}, "Significant Strikes": {"Landed": "19", "Attempts": "31"}, "Body Significant Strikes": {"Landed": "2", "Attempts": "3"}, "Distance Head Strikes": {"Landed": "1", "Attempts": "4"}, "Distance Leg Kicks": {"Landed": "", "Attempts": ""}, "Distance Head Kicks": {"Landed": "", "Attempts": ""}, "Head Significant Strikes": {"Landed": "17", "Attempts": "27"}, "Clinch Significant Kicks": {"Landed": "", "Attempts": ""}}}, "Red": {"Grappling": {"Reversals": {"Landed": "1"}, "Submissions": {"Attempts": "0"}, "Takedowns": {"Landed": "1", "Attempts": "2"}, "Standups": {"Landed": "1"}}, "TIP": {"Guard Control Time": "00:27", "Ground Time": "03:36", "Half Guard Control Time": "00:52", "Standing Time": "01:43", "Mount Control Time": "00:25", "Side Control Time": "00:03", "Ground Control Time": "01:47", "Misc. Ground Control Time": "00:00", "Distance Time": "00:35", "Control Time": "01:52", "Clinch Time": "01:08", "Neutral Time": "00:46", "Back Control Time": "00:00"}, "FighterID": "2626", "Strikes": {"Distance Leg Strikes": {"Landed": "0", "Attempts": "0"}, "Knock Down": {"Landed": "0"}, "Ground Leg Strikes": {"Landed": "0", "Attempts": "0"}, "Clinch Body Strikes": {"Landed": "1", "Attempts": "2"}, "Ground Significant Punches": {"Landed": "", "Attempts": ""}, "Ground Total Strikes": {"Landed": "3", "Attempts": "3"}, "Head Total Strikes": {"Landed": "4", "Attempts": "5"}, "Ground Head Strikes": {"Landed": "0", "Attempts": "0"}, "Distance Head Punches": {"Landed": "", "Attempts": ""}, "Distance Body Punches": {"Landed": "", "Attempts": ""}, "Distance Body Kicks": {"Landed": "", "Attempts": ""}, "Clinch Head Strikes": {"Landed": "0", "Attempts": "0"}, "Kicks": {"Landed": "", "Attempts": ""}, "Body Total Strikes": {"Landed": "2", "Attempts": "4"}, "Total Strikes": {"Landed": "6", "Attempts": "9"}, "Distance Body Strikes": {"Landed": "1", "Attempts": "2"}, "Clinch Significant Strikes": {"Landed": "1", "Attempts": "2"}, "Ground Body Strikes": {"Landed": "0", "Attempts": "0"}, "Legs Significant Strikes": {"Landed": "0", "Attempts": "0"}, "Ground Significant Kicks": {"Landed": "", "Attempts": ""}, "Distance Strikes": {"Landed": "2", "Attempts": "4"}, "Clinch Total Strikes": {"Landed": "1", "Attempts": "2"}, "Clinch Leg Strikes": {"Landed": "0", "Attempts": "0"}, "Punches": {"Landed": "", "Attempts": ""}, "Legs Total Strikes": {"Landed": "0", "Attempts": "0"}, "Ground Significant Strikes": {"Landed": "0", "Attempts": "0"}, "Clinch Significant Punches": {"Landed": "", "Attempts": ""}, "Significant Strikes": {"Landed": "3", "Attempts": "6"}, "Body Significant Strikes": {"Landed": "2", "Attempts": "4"}, "Distance Head Strikes": {"Landed": "1", "Attempts": "2"}, "Distance Leg Kicks": {"Landed": "", "Attempts": ""}, "Distance Head Kicks": {"Landed": "", "Attempts": ""}, "Head Significant Strikes": {"Landed": "1", "Attempts": "2"}, "Clinch Significant Kicks": {"Landed": "", "Attempts": ""}}}}}, "Accolade": "", "CurrentRound": "2", "FightID": "6369", "MaxRounds": "3", "FightStats": {"Blue": {"Grappling": {"Reversals": {"Landed": "1"}, "Submissions": {"Attempts": "0"}, "Takedowns": {"Landed": "3", "Attempts": "3"}, "Standups": {"Landed": "1"}}, "TIP": {"Guard Control Time": "01:09", "Ground Time": "05:24", "Half Guard Control Time": "01:29", "Standing Time": "02:01", "Mount Control Time": "00:59", "Side Control Time": "00:00", "Ground Control Time": "03:37", "Misc. Ground Control Time": "00:00", "Distance Time": "00:53", "Control Time": "04:29", "Clinch Time": "01:08", "Neutral Time": "01:04", "Back Control Time": "00:00"}, "FighterID": "2824", "Strikes": {"Distance Leg Strikes": {"Landed": "1", "Attempts": "2"}, "Knock Down": {"Landed": "0"}, "Ground Leg Strikes": {"Landed": "0", "Attempts": "0"}, "Clinch Body Strikes": {"Landed": "2", "Attempts": "2"}, "Ground Significant Punches": {"Landed": "", "Attempts": ""}, "Ground Total Strikes": {"Landed": "48", "Attempts": "69"}, "Head Total Strikes": {"Landed": "50", "Attempts": "74"}, "Ground Head Strikes": {"Landed": "45", "Attempts": "65"}, "Distance Head Punches": {"Landed": "", "Attempts": ""}, "Distance Body Punches": {"Landed": "", "Attempts": ""}, "Distance Body Kicks": {"Landed": "", "Attempts": ""}, "Clinch Head Strikes": {"Landed": "1", "Attempts": "1"}, "Kicks": {"Landed": "", "Attempts": ""}, "Body Total Strikes": {"Landed": "2", "Attempts": "3"}, "Total Strikes": {"Landed": "55", "Attempts": "81"}, "Distance Body Strikes": {"Landed": "0", "Attempts": "0"}, "Clinch Significant Strikes": {"Landed": "3", "Attempts": "3"}, "Ground Body Strikes": {"Landed": "0", "Attempts": "1"}, "Legs Significant Strikes": {"Landed": "1", "Attempts": "2"}, "Ground Significant Kicks": {"Landed": "", "Attempts": ""}, "Distance Strikes": {"Landed": "2", "Attempts": "7"}, "Clinch Total Strikes": {"Landed": "5", "Attempts": "5"}, "Clinch Leg Strikes": {"Landed": "0", "Attempts": "0"}, "Punches": {"Landed": "", "Attempts": ""}, "Legs Total Strikes": {"Landed": "3", "Attempts": "4"}, "Ground Significant Strikes": {"Landed": "45", "Attempts": "66"}, "Clinch Significant Punches": {"Landed": "", "Attempts": ""}, "Significant Strikes": {"Landed": "50", "Attempts": "76"}, "Body Significant Strikes": {"Landed": "2", "Attempts": "3"}, "Distance Head Strikes": {"Landed": "1", "Attempts": "5"}, "Distance Leg Kicks": {"Landed": "", "Attempts": ""}, "Distance Head Kicks": {"Landed": "", "Attempts": ""}, "Head Significant Strikes": {"Landed": "47", "Attempts": "71"}, "Clinch Significant Kicks": {"Landed": "", "Attempts": ""}}}, "Red": {"Grappling": {"Reversals": {"Landed": "1"}, "Submissions": {"Attempts": "0"}, "Takedowns": {"Landed": "1", "Attempts": "2"}, "Standups": {"Landed": "1"}}, "TIP": {"Guard Control Time": "00:27", "Ground Time": "05:24", "Half Guard Control Time": "00:52", "Standing Time": "02:01", "Mount Control Time": "00:25", "Side Control Time": "00:03", "Ground Control Time": "01:47", "Misc. Ground Control Time": "00:00", "Distance Time": "00:53", "Control Time": "01:52", "Clinch Time": "01:08", "Neutral Time": "01:04", "Back Control Time": "00:00"}, "FighterID": "2626", "Strikes": {"Distance Leg Strikes": {"Landed": "0", "Attempts": "0"}, "Knock Down": {"Landed": "0"}, "Ground Leg Strikes": {"Landed": "0", "Attempts": "0"}, "Clinch Body Strikes": {"Landed": "1", "Attempts": "2"}, "Ground Significant Punches": {"Landed": "", "Attempts": ""}, "Ground Total Strikes": {"Landed": "3", "Attempts": "3"}, "Head Total Strikes": {"Landed": "5", "Attempts": "9"}, "Ground Head Strikes": {"Landed": "0", "Attempts": "0"}, "Distance Head Punches": {"Landed": "", "Attempts": ""}, "Distance Body Punches": {"Landed": "", "Attempts": ""}, "Distance Body Kicks": {"Landed": "", "Attempts": ""}, "Clinch Head Strikes": {"Landed": "0", "Attempts": "0"}, "Kicks": {"Landed": "", "Attempts": ""}, "Body Total Strikes": {"Landed": "2", "Attempts": "4"}, "Total Strikes": {"Landed": "7", "Attempts": "13"}, "Distance Body Strikes": {"Landed": "1", "Attempts": "2"}, "Clinch Significant Strikes": {"Landed": "1", "Attempts": "2"}, "Ground Body Strikes": {"Landed": "0", "Attempts": "0"}, "Legs Significant Strikes": {"Landed": "0", "Attempts": "0"}, "Ground Significant Kicks": {"Landed": "", "Attempts": ""}, "Distance Strikes": {"Landed": "3", "Attempts": "8"}, "Clinch Total Strikes": {"Landed": "1", "Attempts": "2"}, "Clinch Leg Strikes": {"Landed": "0", "Attempts": "0"}, "Punches": {"Landed": "", "Attempts": ""}, "Legs Total Strikes": {"Landed": "0", "Attempts": "0"}, "Ground Significant Strikes": {"Landed": "0", "Attempts": "0"}, "Clinch Significant Punches": {"Landed": "", "Attempts": ""}, "Significant Strikes": {"Landed": "4", "Attempts": "10"}, "Body Significant Strikes": {"Landed": "2", "Attempts": "4"}, "Distance Head Strikes": {"Landed": "2", "Attempts": "6"}, "Distance Leg Kicks": {"Landed": "", "Attempts": ""}, "Distance Head Kicks": {"Landed": "", "Attempts": ""}, "Head Significant Strikes": {"Landed": "2", "Attempts": "6"}, "Clinch Significant Kicks": {"Landed": "", "Attempts": ""}}}}, "Fighters": {"Blue": {"Name": "Alexander Volkanovski", "FighterID": "2824"}, "Red": {"Name": "Yusuke Kasuya", "FighterID": "2626"}}, "Referee": "Greg Kleynjans", "CurrentRoundTime": "02:06", "WeightClass": "Lightweight"}, "Type": "Stats"}