{
    "degree": "", 
    "name": "Hector Sandoval", 
    "weight": "125", 
    "hometown": "Uruapan, Michoacan Mexico", 
    "age": "30", 
    "fights": [], 
    "weight_kg": "56", 
    "strikes": {
        "successful": 38, 
        "attempted": 80, 
        "clinch": 13, 
        "ground": null, 
        "standing": 25
    }, 
    "height": "5' 2\"", 
    "record": "13-3-0", 
    "college": "", 
    "location": "Sacramento, California USA", 
    "height_cm": "157", 
    "fullname": "Hector Sandoval", 
    "summary": [
        "Well-rounded"
    ], 
    "nickname": "Kid Alex", 
    "takedowns": {
        "successful": 2, 
        "attempted": 12, 
        "submissions": 2, 
        "sweeps": 1, 
        "passes": 1
    }
}