{
    "degree": "", 
    "name": "Jason DeLucia", 
    "weight": "190", 
    "hometown": "Bellingham, Massachusetts USA", 
    "age": "", 
    "fights": [], 
    "weight_kg": "86", 
    "strikes": {
        "successful": null, 
        "attempted": null, 
        "clinch": null, 
        "ground": null, 
        "standing": null
    }, 
    "height": "5' 11\"", 
    "record": "", 
    "college": "", 
    "location": "", 
    "height_cm": "180", 
    "fullname": "Jason DeLucia", 
    "summary": [], 
    "nickname": "", 
    "takedowns": {
        "successful": null, 
        "attempted": null, 
        "submissions": 0, 
        "sweeps": 0, 
        "passes": 0
    }
}