{
    "degree": "", 
    "name": "Marcel Fortuna", 
    "weight": "205", 
    "hometown": "Tubarao, Santa Catarina Brazil", 
    "age": "31", 
    "fights": [], 
    "weight_kg": "93", 
    "strikes": {
        "successful": 15, 
        "attempted": 30, 
        "clinch": 4, 
        "ground": null, 
        "standing": 11
    }, 
    "height": "6' 1\"", 
    "record": "9-1-0", 
    "college": "", 
    "location": "Tubarao, Santa Catarina Brazil", 
    "height_cm": "185", 
    "fullname": "Marcel Fortuna", 
    "summary": [
        "Ground Game"
    ], 
    "nickname": "Maozinha", 
    "takedowns": {
        "successful": 0, 
        "attempted": 0, 
        "submissions": 0, 
        "sweeps": 0, 
        "passes": 0
    }
}